larsespenssb_pypitemplate/__init__.py
larsespenssb_pypitemplate/__main__.py
larsespenssb_pypitemplate/functions.py
larsespenssb_pypitemplate/py.typed
larsespenssb_pypitemplate-0.0.1.dist-info/LICENSE
larsespenssb_pypitemplate-0.0.1.dist-info/METADATA
larsespenssb_pypitemplate-0.0.1.dist-info/WHEEL
larsespenssb_pypitemplate-0.0.1.dist-info/entry_points.txt
larsespenssb_pypitemplate-0.0.1.dist-info/RECORD
