Metadata-Version: 2.1
Name: larsespenssb-pypitemplate
Version: 0.0.1
Summary: Larsespenssb Pypitemplate
Home-page: https://github.com/larsespenssb/larsespenssb-pypitemplate
License: MIT
Author: Lars Espen Baanerud
Author-email: Lars.Baanerud@ssb.no
Requires-Python: >=3.9,<4.0
Classifier: Development Status :: 4 - Beta
Classifier: License :: OSI Approved :: MIT License
Classifier: Programming Language :: Python :: 3
Classifier: Programming Language :: Python :: 3.9
Classifier: Programming Language :: Python :: 3.10
Classifier: Programming Language :: Python :: 3.11
Requires-Dist: click (>=8.0.1)
Project-URL: Changelog, https://github.com/larsespenssb/larsespenssb-pypitemplate/releases
Project-URL: Documentation, https://larsespenssb-pypitemplate.readthedocs.io
Project-URL: Repository, https://github.com/larsespenssb/larsespenssb-pypitemplate
